{
  "globalSwitch": false,
  "energyRainConfig": {
    "fixRunTime": [
    ]
  },
  "allSignConfig": {
    "fixRunTime": [
      "02:00",
      "03:00",
      "22:35",
      "23:15"
    ]
  },
  "weLinkConfig": {
    "fixRunTime": [
      "08:50",
      "08:55",
      "09:00",
      "17:30",
      "18:30",
      "20:35"
    ]
  },
  "mainJobConfig": {
    "lastRunTime": "2024-11-02 19:55:00",
    "timeInterval": 180
  },
  "chickenFamilyAndSportConfig": {
    "fixRunTime": [
    ]
  },
  "accountList": [
    {
      "userAccount": "142***@qq.com",
      "userName": "coco"
    },
    {
      "userAccount": "cn_***@163.com",
      "userName": "wm01"
    },
    {
      "userAccount": "173******96",
      "userName": "wm02"
    },
    {
      "userAccount": "173***@163.com",
      "userName": "wm03"
    },
    {
      "userAccount": "173******35",
      "userName": "wm04"
    }
  ]
}
